sidetrack/__init__.py
sidetrack/debug.py
sidetrack-1.4.0.dist-info/LICENSE
sidetrack-1.4.0.dist-info/METADATA
sidetrack-1.4.0.dist-info/WHEEL
sidetrack-1.4.0.dist-info/top_level.txt
sidetrack-1.4.0.dist-info/zip-safe
sidetrack-1.4.0.dist-info/RECORD
