Metadata-Version: 2.1
Name: sidetrack
Version: 1.4.0
Summary: Simple debug tracing package for Python
Home-page: https://github.com/caltechlibrary/sidetrack
Author: Michael Hucka
Author-email: mhucka@caltech.edu
License: BSD 3-clause
Project-URL: Source Code, https://github.com/caltechlibrary/sidetrack
Project-URL: Bug Tracker, https://github.com/caltechlibrary/sidetrack/issues
Keywords: debugging
Platform: UNKNOWN
Classifier: Development Status :: 5 - Production/Stable
Classifier: Environment :: Console
Classifier: License :: OSI Approved :: BSD License
Classifier: Operating System :: MacOS :: MacOS X
Classifier: Operating System :: Microsoft :: Windows
Classifier: Operating System :: POSIX
Classifier: Operating System :: POSIX :: Linux
Classifier: Operating System :: Unix
Classifier: Programming Language :: Python
Classifier: Programming Language :: Python :: 3.6
Classifier: Topic :: Software Development :: Debuggers
Requires-Python: >=3.6
